{
  "title": "Setting Boundaries",
  "description": "A powerful reflection on the unseen cost of people-pleasing, Setting Boundaries challenges the belief that endless giving is a virtue. It reveals how the absence of limits leads to self-abandonment, and how reclaiming one’s inner space is an act of truth, not selfishness. With quiet intensity, the article invites readers to draw sacred lines—not to shut others out, but to finally return to themselves.", 
  "categories": [
    "Wisdom & Character"
  ],
  "cover": "Setting Boundaries.png",
  "date": "2026-03-27"
}